paths_cli/__init__.py
paths_cli/_installed_version.py
paths_cli/cli.py
paths_cli/errors.py
paths_cli/file_copying.py
paths_cli/param_core.py
paths_cli/parameters.py
paths_cli/plugin_management.py
paths_cli/utils.py
paths_cli/version.py
paths_cli/commands/__init__.py
paths_cli/commands/append.py
paths_cli/commands/compile.py
paths_cli/commands/contents.py
paths_cli/commands/equilibrate.py
paths_cli/commands/md.py
paths_cli/commands/pathsampling.py
paths_cli/commands/visit_all.py
paths_cli/commands/wizard.py
paths_cli/compat/__init__.py
paths_cli/compat/openmm.py
paths_cli/compiling/__init__.py
paths_cli/compiling/core.py
paths_cli/compiling/cvs.py
paths_cli/compiling/engines.py
paths_cli/compiling/errors.py
paths_cli/compiling/gendocs.py
paths_cli/compiling/json_type.py
paths_cli/compiling/networks.py
paths_cli/compiling/plugins.py
paths_cli/compiling/root_compiler.py
paths_cli/compiling/schemes.py
paths_cli/compiling/shooting.py
paths_cli/compiling/strategies.py
paths_cli/compiling/tools.py
paths_cli/compiling/topology.py
paths_cli/compiling/volumes.py
paths_cli/compiling/_gendocs/__init__.py
paths_cli/compiling/_gendocs/config_handler.py
paths_cli/compiling/_gendocs/docs_generator.py
paths_cli/compiling/_gendocs/json_type_handlers.py
paths_cli/tests/__init__.py
paths_cli/tests/conftest.py
paths_cli/tests/null_command.py
paths_cli/tests/test_cli.py
paths_cli/tests/test_file_copying.py
paths_cli/tests/test_parameters.py
paths_cli/tests/test_plugin_management.py
paths_cli/tests/test_utils.py
paths_cli/tests/utils.py
paths_cli/tests/commands/__init__.py
paths_cli/tests/commands/conftest.py
paths_cli/tests/commands/test_append.py
paths_cli/tests/commands/test_compile.py
paths_cli/tests/commands/test_contents.py
paths_cli/tests/commands/test_equilibrate.py
paths_cli/tests/commands/test_md.py
paths_cli/tests/commands/test_pathsampling.py
paths_cli/tests/commands/test_visit_all.py
paths_cli/tests/commands/utils.py
paths_cli/tests/compiling/__init__.py
openpathsampling_cli-0.3.1.dist-info/LICENSE
openpathsampling_cli-0.3.1.dist-info/METADATA
openpathsampling_cli-0.3.1.dist-info/WHEEL
openpathsampling_cli-0.3.1.dist-info/entry_points.txt
openpathsampling_cli-0.3.1.dist-info/top_level.txt
openpathsampling_cli-0.3.1.dist-info/RECORD
