Metadata-Version: 2.1
Name: openpathsampling-cli
Version: 0.3.1
Summary: Command line tool for OpenPathSampling
Home-page: https://github.com/openpathsampling/openpathsampling-cli
Author: David W.H. Swenson
Author-email: dwhs@hyperblazer.net
License: MIT
Classifier: License :: OSI Approved :: MIT License
Classifier: Natural Language :: English
Classifier: Operating System :: MacOS :: MacOS X
Classifier: Operating System :: POSIX
Classifier: Programming Language :: Python :: 3
Requires-Python: >=3.10
License-File: LICENSE
Requires-Dist: click
Requires-Dist: tqdm
Requires-Dist: openpathsampling>=1.6
